{
  "pysmithchart": {
    "releases": {
      "0.6.0": [
        {
          "comment_text": "",
          "digests": {
            "md5": "cbbc68dc0dfe8f048bf14c7e88597642",
            "sha256": "b7b419755c264700bcb03e4b651f72a16b5204c6a7d956786baeedc6af4ff92f"
          },
          "downloads": -1,
          "filename": "pysmithchart-0.6.0-py3-none-any.whl",
          "has_sig": false,
          "md5_digest": "cbbc68dc0dfe8f048bf14c7e88597642",
          "packagetype": "bdist_wheel",
          "python_version": "py3",
          "requires_python": ">=3.9",
          "size": 53331,
          "upload_time": "2026-01-29T03:20:18.428781Z",
          "upload_time_iso_8601": "2026-01-29T03:20:18.428781Z",
          "url": "./pysmithchart-0.6.0-py3-none-any.whl",
          "yanked": false,
          "yanked_reason": null
        }
      ]
    }
  }
}